confidentialmind_app_helpers/__init__.py
confidentialmind_app_helpers/llm_api_helpers.py
confidentialmind_app_helpers/streaming.py
confidentialmind_app_helpers/streamlit_utils/__init__.py
confidentialmind_app_helpers/streamlit_utils/app.py
confidentialmind_app_helpers/streamlit_utils/components.py
confidentialmind_app_helpers/streamlit_utils/config_manager_streamlit.py
confidentialmind_app_helpers/streamlit_utils/user.py
confidentialmind_app_helpers/streamlit_utils/media/Favicon.png
confidentialmind_app_helpers/streamlit_utils/media/__init__.py
confidentialmind_app_helpers/streamlit_utils/media/logo.png
confidentialmind_app_helpers-0.1.3.post1.dist-info/LICENSE
confidentialmind_app_helpers-0.1.3.post1.dist-info/METADATA
confidentialmind_app_helpers-0.1.3.post1.dist-info/NOTICE
confidentialmind_app_helpers-0.1.3.post1.dist-info/WHEEL
confidentialmind_app_helpers-0.1.3.post1.dist-info/top_level.txt
confidentialmind_app_helpers-0.1.3.post1.dist-info/RECORD
