Metadata-Version: 2.1
Name: confidentialmind-app-helpers
Version: 0.1.3.post1
Summary: Helper functions for the ConfidentialMind stack, primarily for Streamlit apps
Author-email: confidentialmind <info@confidentialmind.com>
License: Apache-2.0
Project-URL: Homepage, https://www.confidentialmind.com/
Requires-Python: >=3.10
License-File: LICENSE
License-File: NOTICE
Requires-Dist: pydantic >=2.8.2
Requires-Dist: websockets >=12.0
Requires-Dist: requests >=2.32.0
Requires-Dist: Pillow >=9.5.0
Requires-Dist: streamlit >=1.36.0
Requires-Dist: sseclient-py >=1.8.0
Requires-Dist: pyjwt >=2.8.0
Requires-Dist: python-dotenv >=1.0.1
Requires-Dist: confidentialmind-core >=0.1.2
